django_bulk_hooks/__init__.py
django_bulk_hooks/changeset.py
django_bulk_hooks/conditions.py
django_bulk_hooks/constants.py
django_bulk_hooks/context.py
django_bulk_hooks/core/__init__.py
django_bulk_hooks/core/changeset.py
django_bulk_hooks/core/conditions.py
django_bulk_hooks/core/context.py
django_bulk_hooks/core/intent.py
django_bulk_hooks/decorators.py
django_bulk_hooks/dispatcher.py
django_bulk_hooks/dispatcher_executor.py
django_bulk_hooks/dispatcher_preloader.py
django_bulk_hooks/enums.py
django_bulk_hooks/factory.py
django_bulk_hooks/graph.py
django_bulk_hooks/handler.py
django_bulk_hooks/helpers.py
django_bulk_hooks/hooks/__init__.py
django_bulk_hooks/hooks/adapters.py
django_bulk_hooks/hooks/base.py
django_bulk_hooks/hooks/decorators.py
django_bulk_hooks/hooks/requirements.py
django_bulk_hooks/manager.py
django_bulk_hooks/models.py
django_bulk_hooks/operations/__init__.py
django_bulk_hooks/operations/analyzer.py
django_bulk_hooks/operations/bulk_executor.py
django_bulk_hooks/operations/coordinator.py
django_bulk_hooks/operations/field_utils.py
django_bulk_hooks/operations/record_classifier.py
django_bulk_hooks/orchestration/__init__.py
django_bulk_hooks/orchestration/dispatcher.py
django_bulk_hooks/orchestration/executor.py
django_bulk_hooks/orchestration/orchestrator.py
django_bulk_hooks/queryset.py
django_bulk_hooks/registry.py
django_bulk_hooks-0.4.16.dist-info/LICENSE
django_bulk_hooks-0.4.16.dist-info/METADATA
django_bulk_hooks-0.4.16.dist-info/WHEEL
django_bulk_hooks-0.4.16.dist-info/RECORD
