Metadata-Version: 2.3
Name: django-bulk-hooks
Version: 0.4.16
Summary: Hook-style hooks for Django bulk operations like bulk_create and bulk_update.
License: MIT
Keywords: django,bulk,hooks
Author: Konrad Beck
Author-email: konrad.beck@merchantcapital.co.za
Requires-Python: >=3.11,<4.0
Classifier: License :: OSI Approved :: MIT License
Classifier: Programming Language :: Python :: 3
Classifier: Programming Language :: Python :: 3.11
Classifier: Programming Language :: Python :: 3.12
Classifier: Programming Language :: Python :: 3.13
Requires-Dist: django (>=5.2.0,<6.0.0)
Requires-Dist: networkx (>=3.0)
Project-URL: Homepage, https://github.com/AugendLimited/django-bulk-hooks
Project-URL: Repository, https://github.com/AugendLimited/django-bulk-hooks
